admindjango_ckeditor_blog-0.1.dist-info/DESCRIPTION.rst
admindjango_ckeditor_blog-0.1.dist-info/METADATA
admindjango_ckeditor_blog-0.1.dist-info/RECORD
admindjango_ckeditor_blog-0.1.dist-info/WHEEL
admindjango_ckeditor_blog-0.1.dist-info/metadata.json
admindjango_ckeditor_blog-0.1.dist-info/top_level.txt
blog/__init__.py
blog/__init__.pyc
blog/admin.py
blog/admin.pyc
blog/apps.py
blog/models.py
blog/models.pyc
blog/tests.py
blog/views.py
blog/views.pyc
blog/migrations/__init__.py
blog/migrations/__init__.pyc
