Metadata-Version: 2.0
Name: admindjango-ckeditor-blog
Version: 0.1
Summary: django-blogs app to provide you facility to craete a blogs in admin panel
Home-page: https://github.com/rishabh318/django-blog
Author: Rishabh
Author-email: rishabh.khare88@gmail.com
License: UNKNOWN
Download-URL: https://github.com/rishabh318/django-blog/archive/master.zip
Keywords: Blog,Blogs,django,ckeditor
Platform: UNKNOWN
Requires-Dist: Django (==1.11.2)
Requires-Dist: Pillow (==4.1.1)
Requires-Dist: django-ckeditor (==5.2.2)
Requires-Dist: django-multiselectfield (==0.1.7)
Requires-Dist: olefile (==0.44)
Requires-Dist: pytz (==2017.2)
